CHANGES.txt
MANIFEST.in
README.txt
setup.py
collective/__init__.py
collective.simplesocial.egg-info/PKG-INFO
collective.simplesocial.egg-info/SOURCES.txt
collective.simplesocial.egg-info/dependency_links.txt
collective.simplesocial.egg-info/entry_points.txt
collective.simplesocial.egg-info/namespace_packages.txt
collective.simplesocial.egg-info/not-zip-safe
collective.simplesocial.egg-info/requires.txt
collective.simplesocial.egg-info/top_level.txt
collective/simplesocial/__init__.py
collective/simplesocial/configure.zcml
collective/simplesocial/upgrades.py
collective/simplesocial/upgrades.zcml
collective/simplesocial/analytics/__init__.py
collective/simplesocial/analytics/configure.zcml
collective/simplesocial/analytics/feedform.pt
collective/simplesocial/analytics/feedform.py
collective/simplesocial/analytics/like.pt
collective/simplesocial/analytics/like.py
collective/simplesocial/browser/__init__.py
collective/simplesocial/browser/channel.pt
collective/simplesocial/browser/configlet.pt
collective/simplesocial/browser/configlet.py
collective/simplesocial/browser/configure.zcml
collective/simplesocial/browser/facebook_icon.png
collective/simplesocial/browser/fb_init.pt
collective/simplesocial/browser/fb_init.py
collective/simplesocial/browser/image.py
collective/simplesocial/browser/interfaces.py
collective/simplesocial/browser/simplesocial.css
collective/simplesocial/browser/simplesocial.js
collective/simplesocial/browser/thumbnail.py
collective/simplesocial/fanbox/__init__.py
collective/simplesocial/fanbox/configure.zcml
collective/simplesocial/fanbox/facebookfanbox.pt
collective/simplesocial/fanbox/facebookfanbox.py
collective/simplesocial/fanpage_post/__init__.py
collective/simplesocial/fanpage_post/configure.zcml
collective/simplesocial/fanpage_post/fanpage_post.py
collective/simplesocial/fanpage_post/simplesocial_fanpage_post.js
collective/simplesocial/feedform/__init__.py
collective/simplesocial/feedform/configure.zcml
collective/simplesocial/feedform/dataproviders.py
collective/simplesocial/feedform/facebookfeedform.pt
collective/simplesocial/feedform/facebookfeedform.py
collective/simplesocial/likebutton/__init__.py
collective/simplesocial/likebutton/configure.zcml
collective/simplesocial/likebutton/interfaces.py
collective/simplesocial/likebutton/likebutton.pt
collective/simplesocial/likebutton/likebutton.py
