Metadata-Version: 1.1
Name: collective.simplesocial
Version: 1.8
Summary: Basic Facebook Connect support for Plone
Home-page: http://plone.org/products/simplesocial
Author: Groundwire
Author-email: info@groundwire.org
License: GPL
Keywords: facebook connect social network feed fan
Platform: UNKNOWN
Classifier: Framework :: Plone
Classifier: Intended Audience :: Developers
Classifier: Topic :: Software Development :: Libraries :: Python Modules
Classifier: License :: OSI Approved :: GNU General Public License (GPL)
